{"metadata": {"dbt_schema_version": "https://schemas.getdbt.com/dbt/run-results/v6.json", "dbt_version": "1.8.8", "generated_at": "2024-11-22T00:28:31.975421Z", "invocation_id": "3c9b798b-1154-4dd2-9995-0d14227760cd", "env": {}}, "results": [{"status": "success", "timing": [{"name": "compile", "started_at": "2024-11-22T00:28:31.955243Z", "completed_at": "2024-11-22T00:28:31.960442Z"}, {"name": "execute", "started_at": "2024-11-22T00:28:31.960664Z", "completed_at": "2024-11-22T00:28:31.960673Z"}], "thread_id": "Thread-1 (worker)", "execution_time": 0.011535167694091797, "adapter_response": {}, "message": null, "failures": null, "unique_id": "model.sample_project.staging_customers", "compiled": true, "compiled_code": "\n\nselect *\nfrom \"raw\".\"silver\".\"customers\"", "relation_name": "\"dev\".\"main\".\"staging_customers\""}, {"status": "success", "timing": [{"name": "compile", "started_at": "2024-11-22T00:28:31.963359Z", "completed_at": "2024-11-22T00:28:31.965926Z"}, {"name": "execute", "started_at": "2024-11-22T00:28:31.966122Z", "completed_at": "2024-11-22T00:28:31.966128Z"}], "thread_id": "Thread-1 (worker)", "execution_time": 0.0045850276947021484, "adapter_response": {}, "message": null, "failures": null, "unique_id": "model.sample_project.staging_orders", "compiled": true, "compiled_code": "\n\nselect *\nfrom (\n\t\"raw\".\"silver\".\"products\" as t0\njoin\n\t\"raw\".\"silver\".\"customers\" as t1\n)", "relation_name": "\"dev\".\"main\".\"staging_orders\""}, {"status": "success", "timing": [{"name": "compile", "started_at": "2024-11-22T00:28:31.967240Z", "completed_at": "2024-11-22T00:28:31.968923Z"}, {"name": "execute", "started_at": "2024-11-22T00:28:31.969101Z", "completed_at": "2024-11-22T00:28:31.969105Z"}], "thread_id": "Thread-1 (worker)", "execution_time": 0.0024559497833251953, "adapter_response": {}, "message": null, "failures": null, "unique_id": "model.sample_project.staging_sales", "compiled": true, "compiled_code": "\n\nselect *\nfrom \"raw\".\"silver\".\"orders\"", "relation_name": "\"dev\".\"main\".\"staging_sales\""}, {"status": "success", "timing": [{"name": "compile", "started_at": "2024-11-22T00:28:31.969982Z", "completed_at": "2024-11-22T00:28:31.971524Z"}, {"name": "execute", "started_at": "2024-11-22T00:28:31.971772Z", "completed_at": "2024-11-22T00:28:31.971775Z"}], "thread_id": "Thread-1 (worker)", "execution_time": 0.0021979808807373047, "adapter_response": {}, "message": null, "failures": null, "unique_id": "model.sample_project.analytics_customers", "compiled": true, "compiled_code": "\n\nselect *\nfrom \"dev\".\"main\".\"staging_orders\"", "relation_name": "\"dev\".\"main\".\"analytics_customers\""}, {"status": "success", "timing": [{"name": "compile", "started_at": "2024-11-22T00:28:31.972589Z", "completed_at": "2024-11-22T00:28:31.974381Z"}, {"name": "execute", "started_at": "2024-11-22T00:28:31.974546Z", "completed_at": "2024-11-22T00:28:31.974549Z"}], "thread_id": "Thread-1 (worker)", "execution_time": 0.0023012161254882812, "adapter_response": {}, "message": null, "failures": null, "unique_id": "model.sample_project.analytics_sales", "compiled": true, "compiled_code": "\n\nselect *\nfrom \"dev\".\"main\".\"staging_sales\"", "relation_name": "\"dev\".\"main\".\"analytics_sales\""}], "elapsed_time": 0.16392111778259277, "args": {"send_anonymous_usage_stats": true, "compile": true, "enable_legacy_logger": false, "defer": false, "log_file_max_bytes": 10485760, "print": true, "strict_mode": false, "vars": {}, "source_freshness_run_project_hooks": false, "log_level": "info", "macro_debugging": false, "quiet": false, "printer_width": 80, "indirect_selection": "eager", "log_path": "/Users/ranasalal.ali/project-repos/PoCs/lineage-generator/output/dbt_sample_project/logs", "introspect": true, "show_resource_report": false, "which": "generate", "write_json": true, "favor_state": false, "cache_selected_only": false, "empty_catalog": false, "profiles_dir": "/Users/ranasalal.ali/project-repos/PoCs/lineage-generator/output/dbt_sample_project", "log_format": "default", "warn_error_options": {"include": [], "exclude": []}, "project_dir": "/Users/ranasalal.ali/project-repos/PoCs/lineage-generator/output/dbt_sample_project", "static": false, "exclude": [], "invocation_command": "dbt docs generate", "require_explicit_package_overrides_for_builtin_materializations": true, "select": [], "use_colors_file": true, "require_resource_names_without_spaces": false, "use_colors": true, "log_level_file": "debug", "log_format_file": "debug", "partial_parse": true, "version_check": true, "populate_cache": true, "partial_parse_file_diff": true, "static_parser": true}}